ohunerin/__init__.py
ohunerin/__main__.py
ohunerin/args.py
ohunerin/audio.py
ohunerin/detector.py
ohunerin/listener.py
ohunerin/logger.py
ohunerin/models.py
ohunerin/mqtt.py
ohunerin/package.py
ohunerin/string.py
oremi_ohunerin_listener-2.0.0.dist-info/LICENSE
oremi_ohunerin_listener-2.0.0.dist-info/LICENSE_HEADER.txt
oremi_ohunerin_listener-2.0.0.dist-info/METADATA
oremi_ohunerin_listener-2.0.0.dist-info/WHEEL
oremi_ohunerin_listener-2.0.0.dist-info/entry_points.txt
oremi_ohunerin_listener-2.0.0.dist-info/RECORD
