Metadata-Version: 2.3
Name: oremi-ohunerin-listener
Version: 2.0.0
Summary: Oremi Ohunerin Listener bridges Oremi Ohunerin's real-time audio detection with MQTT, enabling seamless integration into home automation systems like Home Assistant
Home-page: https://gitlab.com/demsking/oremi-ohunerin-listener
License: Apache-2.0
Keywords: ohunerin,listener,sound,detection,wakeword,mqtt
Author: Sébastien Demanou
Author-email: demsking@gmail.com
Requires-Python: >=3.11,<3.12
Classifier: Environment :: Console
Classifier: Intended Audience :: Developers
Classifier: License :: OSI Approved :: Apache Software License
Classifier: Natural Language :: English
Classifier: Natural Language :: French
Classifier: Programming Language :: Python :: 3
Classifier: Programming Language :: Python :: 3.11
Classifier: Topic :: Software Development :: Libraries :: Python Modules
Requires-Dist: dataclasses-json (>=0.6.7,<0.7.0)
Requires-Dist: oremi-core (>=1.2.1,<2.0.0)
Requires-Dist: paho-mqtt (>=2.1.0,<3.0.0)
Requires-Dist: sounddevice (>=0.5.1,<0.6.0)
Requires-Dist: websockets (>=14.1,<15.0)
Project-URL: Documentation, https://gitlab.com/demsking/oremi-ohunerin-listener/-/blob/main/README.md
Project-URL: Repository, https://gitlab.com/demsking/oremi-ohunerin-listener
Project-URL: Say Thanks!, https://www.buymeacoffee.com/demsking
Project-URL: Source, https://gitlab.com/demsking/oremi-ohunerin-listener
Project-URL: Tracker, https://gitlab.com/demsking/oremi-ohunerin-listener/-/issues
